LICENSE
lazytracker/__init__.py
lazytracker/lazytracker.py
lazytracker/tracked.py
lazytracker-0.2.0.dist-info/LICENSE
lazytracker-0.2.0.dist-info/WHEEL
lazytracker-0.2.0.dist-info/METADATA
lazytracker-0.2.0.dist-info/RECORD
